nmdc_runtime/Dockerfile
nmdc_runtime/__init__.py
nmdc_runtime/config.py
nmdc_runtime/main.py
nmdc_runtime/mongo_util.py
nmdc_runtime/util.py
nmdc_runtime/api/__init__.py
nmdc_runtime/api/analytics.py
nmdc_runtime/api/entrypoint.sh
nmdc_runtime/api/main.py
nmdc_runtime/api/middleware.py
nmdc_runtime/api/openapi.py
nmdc_runtime/api/boot/__init__.py
nmdc_runtime/api/boot/capabilities.py
nmdc_runtime/api/boot/object_types.py
nmdc_runtime/api/boot/triggers.py
nmdc_runtime/api/boot/workflows.py
nmdc_runtime/api/core/__init__.py
nmdc_runtime/api/core/auth.py
nmdc_runtime/api/core/idgen.py
nmdc_runtime/api/core/metadata.py
nmdc_runtime/api/core/util.py
nmdc_runtime/api/db/__init__.py
nmdc_runtime/api/db/mongo.py
nmdc_runtime/api/db/s3.py
nmdc_runtime/api/endpoints/__init__.py
nmdc_runtime/api/endpoints/allowances.py
nmdc_runtime/api/endpoints/capabilities.py
nmdc_runtime/api/endpoints/find.py
nmdc_runtime/api/endpoints/jobs.py
nmdc_runtime/api/endpoints/metadata.py
nmdc_runtime/api/endpoints/nmdcschema.py
nmdc_runtime/api/endpoints/object_types.py
nmdc_runtime/api/endpoints/objects.py
nmdc_runtime/api/endpoints/operations.py
nmdc_runtime/api/endpoints/queries.py
nmdc_runtime/api/endpoints/runs.py
nmdc_runtime/api/endpoints/search.py
nmdc_runtime/api/endpoints/sites.py
nmdc_runtime/api/endpoints/triggers.py
nmdc_runtime/api/endpoints/users.py
nmdc_runtime/api/endpoints/util.py
nmdc_runtime/api/endpoints/wf_file_staging.py
nmdc_runtime/api/endpoints/workflows.py
nmdc_runtime/api/endpoints/lib/__init__.py
nmdc_runtime/api/endpoints/lib/helpers.py
nmdc_runtime/api/endpoints/lib/linked_instances.py
nmdc_runtime/api/endpoints/lib/path_segments.py
nmdc_runtime/api/models/__init__.py
nmdc_runtime/api/models/allowance.py
nmdc_runtime/api/models/capability.py
nmdc_runtime/api/models/id.py
nmdc_runtime/api/models/job.py
nmdc_runtime/api/models/metadata.py
nmdc_runtime/api/models/minter.py
nmdc_runtime/api/models/nmdc_schema.py
nmdc_runtime/api/models/object.py
nmdc_runtime-2.13.0.dist-info/METADATA
nmdc_runtime-2.13.0.dist-info/WHEEL
nmdc_runtime-2.13.0.dist-info/entry_points.txt
nmdc_runtime-2.13.0.dist-info/licenses/LICENSE
nmdc_runtime-2.13.0.dist-info/RECORD
