Metadata-Version: 2.4
Name: nmdc-runtime
Version: 2.13.0
Summary: A runtime system for NMDC data management and orchestration
Project-URL: Changelog, https://github.com/microbiomedata/nmdc-runtime/releases
Project-URL: Documentation, https://docs.microbiomedata.org/runtime
Project-URL: Issues, https://github.com/microbiomedata/nmdc-runtime/issues
Project-URL: Repository, https://github.com/microbiomedata/nmdc-runtime
License-File: LICENSE
Requires-Python: >=3.10
Requires-Dist: base32-lib
Requires-Dist: boto3
Requires-Dist: click
Requires-Dist: dagit
Requires-Dist: dagster
Requires-Dist: dagster-graphql
Requires-Dist: dagster-postgres
Requires-Dist: fastapi>=0.115.0
Requires-Dist: frozendict
Requires-Dist: git-root
Requires-Dist: jq
Requires-Dist: jsonasobj2
Requires-Dist: linkml
Requires-Dist: linkml-runtime
Requires-Dist: lxml
Requires-Dist: nmdc-schema==11.14.0
Requires-Dist: ontology-loader==0.2.2
Requires-Dist: pandas
Requires-Dist: passlib[bcrypt]
Requires-Dist: pydantic[email]>=1.10.0
Requires-Dist: pyinstrument
Requires-Dist: pymongo
Requires-Dist: python-dotenv
Requires-Dist: python-jose[cryptography]
Requires-Dist: python-multipart>=0.0.18
Requires-Dist: pyyaml
Requires-Dist: refscan==0.3.2
Requires-Dist: requests
Requires-Dist: requests-cache
Requires-Dist: scalar-fastapi<2.0.0,>=1.4.1
Requires-Dist: sentry-sdk[fastapi]<3.0.0,>=2.0.0
Requires-Dist: tenacity
Requires-Dist: toolz
Requires-Dist: tqdm
Requires-Dist: unidecode
Requires-Dist: uvicorn[standard]
